jvcprojector/__init__.py
jvcprojector/command.py
jvcprojector/connection.py
jvcprojector/const.py
jvcprojector/device.py
jvcprojector/error.py
jvcprojector/projector.py
jvcprojector/py.typed
pyjvcprojector-1.1.2.dist-info/LICENSE
pyjvcprojector-1.1.2.dist-info/METADATA
pyjvcprojector-1.1.2.dist-info/WHEEL
pyjvcprojector-1.1.2.dist-info/top_level.txt
pyjvcprojector-1.1.2.dist-info/RECORD
