Metadata-Version: 2.1
Name: pyjvcprojector
Version: 1.1.2
Summary: "A python library for controlling a JVC Projector over a network connection."
Home-page: https://github.com/SteveEasley/pyjvcprojector
Author: Steve Easley
Author-email: tardis74@yahoo.com
Classifier: Development Status :: 4 - Beta
Classifier: Intended Audience :: Developers
Classifier: License :: OSI Approved :: MIT License
Classifier: Topic :: Home Automation
Classifier: Topic :: Software Development :: Libraries
Classifier: Programming Language :: Python :: 3.10
License-File: LICENSE
Requires-Dist: aiodns>=3.2.0
